dropbox/__init__.py
dropbox/base.py
dropbox/file.py
dropbox/shared_link.py
dropbox/user.py
dropbox_api-0.2.6.dist-info/METADATA
dropbox_api-0.2.6.dist-info/WHEEL
dropbox_api-0.2.6.dist-info/top_level.txt
dropbox_api-0.2.6.dist-info/RECORD
